pyexlion/Compounder.py
pyexlion/PsdParseInfo.py
pyexlion/PsdParser.py
pyexlion/__init__.py
pyexlion-0.1.8.dist-info/LICENSE
pyexlion-0.1.8.dist-info/METADATA
pyexlion-0.1.8.dist-info/WHEEL
pyexlion-0.1.8.dist-info/top_level.txt
pyexlion-0.1.8.dist-info/RECORD
