Metadata-Version: 2.1
Name: pyexlion
Version: 0.1.8
Summary: lion package
Home-page: https://github.com/patrickxu1986/pylion
Author: patrickxu
Author-email: xcpxcp198608@163.com
Project-URL: Bug Tracker, https://github.com/patrickxu1986/pylion/issues
Classifier: Programming Language :: Python :: 3
Classifier: License :: OSI Approved :: MIT License
Classifier: Operating System :: OS Independent
Requires-Python: >=3.6
License-File: LICENSE
Requires-Dist: pygalaxy (>=0.3.6)
Requires-Dist: Pillow (>=9.3.0)
Requires-Dist: psd-tools (>=1.9.23)
